useckit/Evaluators.py
useckit/__init__.py
useckit/evaluation/__init__.py
useckit/evaluation/identification.py
useckit/evaluation/identification_with_reject.py
useckit/evaluation/verification.py
useckit/paradigms/__init__.py
useckit/paradigms/_paradigm_base.py
useckit/paradigms/anomaly_detection/__init__.py
useckit/paradigms/anomaly_detection/anomaly_paradigm.py
useckit/paradigms/anomaly_detection/evaluation_methods/__init__.py
useckit/paradigms/anomaly_detection/evaluation_methods/_fixed_false_negative_thresholding_method.py
useckit/paradigms/anomaly_detection/evaluation_methods/anomaly_evaluation_method_base.py
useckit/paradigms/anomaly_detection/evaluation_methods/identification.py
useckit/paradigms/anomaly_detection/evaluation_methods/identification_with_reject.py
useckit/paradigms/anomaly_detection/evaluation_methods/legacy_identification_with_reject.py
useckit/paradigms/anomaly_detection/evaluation_methods/verification.py
useckit/paradigms/anomaly_detection/prediction_models/__init__.py
useckit/paradigms/anomaly_detection/prediction_models/anomaly_prediction_model_base.py
useckit/paradigms/anomaly_detection/prediction_models/auto_encoder_keras_prediction_model.py
useckit/paradigms/anomaly_detection/prediction_models/keras_model_descriptions.py
useckit/paradigms/anomaly_detection/prediction_models/scikit_anomaly_prediction_model.py
useckit/paradigms/anomaly_detection/prediction_models/scikit_model_descriptions.py
useckit/paradigms/binary_verification/__init__.py
useckit/paradigms/binary_verification/binary_verification_paradigm.py
useckit/paradigms/binary_verification/evaluation_methods/__init__.py
useckit/paradigms/binary_verification/evaluation_methods/binary_verification_evaluation_method_base.py
useckit/paradigms/binary_verification/evaluation_methods/binary_verification_evaluation_method_scoring.py
useckit/paradigms/binary_verification/prediction_models/__init__.py
useckit-0.4.22.dist-info/LICENSE
useckit-0.4.22.dist-info/METADATA
useckit-0.4.22.dist-info/WHEEL
useckit-0.4.22.dist-info/top_level.txt
useckit-0.4.22.dist-info/RECORD
