Metadata-Version: 2.1
Name: useckit
Version: 0.4.22
Home-page: https://blindforreview.com
Author: BlindForReview.com
Author-email: mail@blindforreview.com
Classifier: Programming Language :: Python :: 3
Classifier: License :: OSI Approved :: GNU General Public License v3 (GPLv3)
Classifier: Operating System :: OS Independent
Requires-Python: >=3.9
License-File: LICENSE
Requires-Dist: tensorflow ==2.15.1
Requires-Dist: pandas >=1.2.0
Requires-Dist: matplotlib >=3.3.0
Requires-Dist: tqdm >=4.56.0
Requires-Dist: scikit-learn >=0.24.0
Requires-Dist: wheel
Requires-Dist: twine
Requires-Dist: numpy
Requires-Dist: dill
Requires-Dist: jupyter
Requires-Dist: xgboost
Requires-Dist: natsort
